ATG/__init__.py
ATG/api/__init__.py
ATG/api/account_v1.py
ATG/api/ddragon.py
ATG/api/league_v4.py
ATG/api/match_v5.py
ATG/api/spectator_v5.py
ATG/api/summoner_v4.py
ATG/api/utils.py
ATG/database/__init__.py
ATG/database/database.py
ATG/match_lib/__init__.py
ATG/match_lib/esports_ingest.py
ATG/match_lib/ingest_match.py
ATG/models/__init__.py
ATG/models/account.py
ATG/models/base.py
ATG/models/champion.py
ATG/models/draft_event.py
ATG/models/game.py
ATG/models/game_event.py
ATG/models/participant.py
ATG/models/participant_stat.py
ATG/models/player.py
ATG/models/player_team_association.py
ATG/models/series.py
ATG/models/team.py
ATG/models/team_dto.py
ATG/models/team_stat.py
ATG/models/tournament.py
ATG/rate_limiter/README.md
ATG/rate_limiter/__init__.py
ATG/rate_limiter/rate_limiter.py
ATG/utils/__init__.py
ATG/utils/constants.py
ATG/utils/helpers.py
atg_lib-1.5.6.dist-info/LICENSE
atg_lib-1.5.6.dist-info/METADATA
atg_lib-1.5.6.dist-info/WHEEL
atg_lib-1.5.6.dist-info/RECORD
