Metadata-Version: 2.3
Name: ATG-lib
Version: 1.5.6
Summary: Python library to process solo queue game data with comprehensive database models to additionally store LoL Esports data
License: GPL-3.0-or-later
Author: Allan Cao
Author-email: allan@allancao.ca
Requires-Python: >=3.10
Classifier: License :: OSI Approved :: GNU General Public License v3 or later (GPLv3+)
Classifier: Programming Language :: Python :: 3
Classifier: Programming Language :: Python :: 3.10
Classifier: Programming Language :: Python :: 3.11
Classifier: Programming Language :: Python :: 3.12
Classifier: Programming Language :: Python :: 3.13
Requires-Dist: psycopg (>=3.2.9,<4.0.0)
Requires-Dist: requests (>=2.32.4,<3.0.0)
Requires-Dist: sqlalchemy (>=2.0.41,<3.0.0)
Requires-Dist: tqdm (>=4.67.1,<5.0.0)
